streamlit_text_toggle/__init__.py
streamlit_text_toggle/example.py
streamlit_text_toggle/frontend/build/asset-manifest.json
streamlit_text_toggle/frontend/build/bootstrap.min.css
streamlit_text_toggle/frontend/build/index.html
streamlit_text_toggle/frontend/build/static/js/main.00363db4.js
streamlit_text_toggle/frontend/build/static/js/main.00363db4.js.LICENSE.txt
streamlit_text_toggle/frontend/build/static/js/main.00363db4.js.map
streamlit_text_toggle/frontend/build/static/js/main.952a21ba.js
streamlit_text_toggle/frontend/build/static/js/main.952a21ba.js.LICENSE.txt
streamlit_text_toggle/frontend/build/static/js/main.952a21ba.js.map
streamlit_text_toggle-0.0.9.dist-info/LICENSE
streamlit_text_toggle-0.0.9.dist-info/METADATA
streamlit_text_toggle-0.0.9.dist-info/WHEEL
streamlit_text_toggle-0.0.9.dist-info/top_level.txt
streamlit_text_toggle-0.0.9.dist-info/RECORD
